{
  "updatedAt": "2026-04-24T15:05:24+08:00",
  "sessionKey": "agent:main:telegram:direct:6018252086",
  "sessionId": "34e13467-0fe4-46bb-a4c7-8c5e1d49a88d",
  "source": "sessions-store",
  "percentUsed": null,
  "totalTokens": null,
  "contextTokens": null,
  "remainingTokens": null,
  "warningThreshold": 40,
  "snapshotThreshold": 48,
  "pressureState": "unknown",
  "lastSnapshotHash": "a48a430f4c68ac70353b32d7ac29122781588917cd499d84ad762c4d047ce4e8",
  "lastSnapshotAt": "2026-04-24T14:57:36+08:00",
  "shouldSnapshot": false
}
